[
  {
    "sheet": "Login",
    "cell": "A1",
    "image": "image1.png",
    "title": "Picture 1",
    "desc": ""
  },
  {
    "sheet": "Login",
    "cell": "A33",
    "image": "image2.png",
    "title": "Picture 3",
    "desc": ""
  },
  {
    "sheet": "Sheet5",
    "cell": "A2",
    "image": "image3.png",
    "title": "Picture 1",
    "desc": ""
  },
  {
    "sheet": "Sheet7",
    "cell": "A4",
    "image": "image4.png",
    "title": "Picture 1",
    "desc": ""
  },
  {
    "sheet": "Sheet7",
    "cell": "A22",
    "image": "image5.png",
    "title": "Picture 2",
    "desc": ""
  },
  {
    "sheet": "Sheet8",
    "cell": "A7",
    "image": "image6.png",
    "title": "Picture 1",
    "desc": ""
  },
  {
    "sheet": "Sheet8",
    "cell": "A26",
    "image": "image7.png",
    "title": "Picture 2",
    "desc": ""
  },
  {
    "sheet": "Sheet9",
    "cell": "A4",
    "image": "image8.png",
    "title": "Picture 1",
    "desc": ""
  },
  {
    "sheet": "Sheet10",
    "cell": "A2",
    "image": "image9.png",
    "title": "Picture 1",
    "desc": ""
  }
]